maxiverse/__init__.py
maxiverse/base/__init__.py
maxiverse/base/abstract_base.py
maxiverse/classifier/__init__.py
maxiverse/classifier/evaluator.py
maxiverse-0.0.5.dist-info/LICENSE
maxiverse-0.0.5.dist-info/METADATA
maxiverse-0.0.5.dist-info/WHEEL
maxiverse-0.0.5.dist-info/top_level.txt
maxiverse-0.0.5.dist-info/RECORD
