Metadata-Version: 2.1
Name: maxiverse
Version: 0.0.5
Summary: UNKNOWN
Home-page: UNKNOWN
Author: Balavignesh M
Author-email: crystelpheonix@gmail.com
License: UNKNOWN
Platform: UNKNOWN
Classifier: Programming Language :: Python :: 3
Classifier: License :: OSI Approved :: MIT License
Classifier: Operating System :: OS Independent
Requires-Python: >=3.6
License-File: LICENSE
Requires-Dist: scikit-learn
Requires-Dist: pandas
Requires-Dist: xgboost
